mdit_py_emoji/__init__.py
mdit_py_emoji/data.py
mdit_py_emoji/rule.py
mdit_py_emoji-0.1.1.dist-info/WHEEL
mdit_py_emoji-0.1.1.dist-info/METADATA
mdit_py_emoji-0.1.1.dist-info/licenses/LICENSE
mdit_py_emoji-0.1.1.dist-info/RECORD
