Metadata-Version: 2.1
Name: mdit-py-emoji
Version: 0.1.1
Summary: Emoji plugin for markdown-it-py.
License: MIT
Author-email: BlueGlassBlock <blueglassblock@outlook.com>
Requires-Python: >=3.8
Classifier: Operating System :: OS Independent
Classifier: Programming Language :: Python :: 3
Requires-Dist: markdown-it-py<4.0.0,>=1.0.0
